fastapi_mctools/__init__.py
fastapi_mctools/cache/__init__.py
fastapi_mctools/cache/base.py
fastapi_mctools/cache/memory.py
fastapi_mctools/cache/redis.py
fastapi_mctools/commands/__init__.py
fastapi_mctools/commands/_templates/async_session.py-tpl
fastapi_mctools/commands/_templates/gitignore-tpl
fastapi_mctools/commands/_templates/gunicorn.config.py-tpl
fastapi_mctools/commands/_templates/main.py-tpl
fastapi_mctools/commands/_templates/pre-commit-tpl
fastapi_mctools/commands/_templates/routers.py-tpl
fastapi_mctools/commands/_templates/session.py-tpl
fastapi_mctools/commands/_templates/settings.py-tpl
fastapi_mctools/commands/_templates/sqlalchemy_base.py-tpl
fastapi_mctools/commands/gunicorn.py
fastapi_mctools/commands/main.py
fastapi_mctools/commands/run.py
fastapi_mctools/commands/shell.py
fastapi_mctools/commands/startproject.py
fastapi_mctools/commands/types.py
fastapi_mctools/db/__init__.py
fastapi_mctools/db/sqlalchemy.py
fastapi_mctools/dependencies.py
fastapi_mctools/exceptions.py
fastapi_mctools/lifespan.py
fastapi_mctools/middlewares/__init__.py
fastapi_mctools/middlewares/logging.py
fastapi_mctools/middlewares/trustedhost.py
fastapi_mctools/orms/__init__.py
fastapi_mctools/orms/sqlalchemy/__init__.py
fastapi_mctools/orms/sqlalchemy/async_base.py
fastapi_mctools/orms/sqlalchemy/filters.py
fastapi_mctools/orms/sqlalchemy/sync_base.py
fastapi_mctools/test_tools/__init__.py
fastapi_mctools/test_tools/db_managers.py
fastapi_mctools/utils/__init__.py
fastapi_mctools/utils/requests.py
fastapi_mctools/utils/responses.py
fastapi_mctools/utils/time.py
fastapi_mctools-0.5.2.dist-info/WHEEL
fastapi_mctools-0.5.2.dist-info/entry_points.txt
fastapi_mctools-0.5.2.dist-info/METADATA
fastapi_mctools-0.5.2.dist-info/RECORD
