Metadata-Version: 2.3
Name: fastapi-mctools
Version: 0.5.2
Summary: Fastapi mc style tools to make it easier to develop.
Author: Jungminchae
Author-email: Jungminchae <minchae3618@gmail.com>
Requires-Dist: boto3>=1.38.23
Requires-Dist: click>=8.2.1
Requires-Dist: fastapi>=0.115.12
Requires-Dist: httpx>=0.28.1
Requires-Dist: redis>=6.1.0
Requires-Dist: sqlalchemy[asyncio]>=2.0.41
Requires-Python: >=3.10, <4.0
